topostats/__init__.py
topostats/_version.py
topostats/array_manipulation.py
topostats/config.py
topostats/default_config.yaml
topostats/entry_point.py
topostats/filters.py
topostats/grains.py
topostats/grainstats.py
topostats/io.py
topostats/plotting.py
topostats/plotting_dictionary.yaml
topostats/plottingfuncs.py
topostats/processing.py
topostats/run_modules.py
topostats/scars.py
topostats/simple_config.yaml
topostats/statistics.py
topostats/summary_config.yaml
topostats/theme.py
topostats/thresholds.py
topostats/topostats.mplstyle
topostats/unet_masking.py
topostats/utils.py
topostats/validation.py
topostats/var_to_label.yaml
topostats/logs/__init__.py
topostats/logs/logs.py
topostats/measure/curvature.py
topostats/measure/feret.py
topostats/measure/geometry.py
topostats/measure/height_profiles.py
topostats/tracing/__init__.py
topostats/tracing/disordered_tracing.py
topostats/tracing/dnacurvature.py
topostats/tracing/nodestats.py
topostats/tracing/ordered_tracing.py
topostats/tracing/pruning.py
topostats/tracing/skeletonize.py
topostats/tracing/splining.py
topostats/tracing/tracingfuncs.py
topostats-2.3.2.dist-info/licenses/COPYING
topostats-2.3.2.dist-info/licenses/COPYING.LESSER
topostats-2.3.2.dist-info/METADATA
topostats-2.3.2.dist-info/WHEEL
topostats-2.3.2.dist-info/entry_points.txt
topostats-2.3.2.dist-info/top_level.txt
topostats-2.3.2.dist-info/RECORD
