Metadata-Version: 2.4
Name: topostats
Version: 2.3.2
Summary: Automated Analysis for Atomic Force Microscopy Images of Biomolecules
Author-email: TopoStats Team <topostats@sheffield.ac.uk>, Alice Pyne <a.l.pyne@sheffield.ac.uk>, Sylvia Whittle <sylvia.whittle@sheffield.ac.uk>, Neil Shephard <n.shephard@sheffield.ac.uk>, Max Gamill <mcgamill1@sheffield.ac.uk>, Jean Du <mdu12@sheffield.ac.uk>
License: GPL-3.0-only
Project-URL: Source, https://github.com/AFM-SPM/TopoStats
Project-URL: Bug_Tracker, https://github.com/AFM-SPM/TopoStats/issues
Project-URL: Documentation, https://AFM-SPM.github.io/TopoStats
Keywords: afm,atomic force microscopy,image processing
Classifier: Programming Language :: Python :: 3
Classifier: Programming Language :: Python :: 3.10
Classifier: Programming Language :: Python :: 3.11
Classifier: Natural Language :: English
Classifier: Operating System :: OS Independent
Classifier: Intended Audience :: Science/Research
Requires-Python: <3.12,>=3.10
License-File: COPYING
License-File: COPYING.LESSER
Requires-Dist: art
Requires-Dist: AFMReader
Requires-Dist: h5py
Requires-Dist: keras
Requires-Dist: matplotlib
Requires-Dist: numpy~=2.0.0
Requires-Dist: numpyencoder
Requires-Dist: pandas
Requires-Dist: pillow<=11.1.0
Requires-Dist: pyyaml
Requires-Dist: ruamel.yaml
Requires-Dist: schema
Requires-Dist: scikit-image
Requires-Dist: scipy
Requires-Dist: seaborn
Requires-Dist: skan
Requires-Dist: snoop
Requires-Dist: tensorflow
Requires-Dist: topoly
Requires-Dist: tqdm
Provides-Extra: tests
Requires-Dist: pytest; extra == "tests"
Requires-Dist: pytest-cov; extra == "tests"
Requires-Dist: pytest-github-actions-annotate-failures; extra == "tests"
Requires-Dist: pytest-mpl; extra == "tests"
Requires-Dist: pytest-regtest==2.3.1; extra == "tests"
Requires-Dist: pytest-xdist; extra == "tests"
Requires-Dist: filetype; extra == "tests"
Provides-Extra: docs
Requires-Dist: Sphinx; extra == "docs"
Requires-Dist: myst_parser; extra == "docs"
Requires-Dist: numpydoc; extra == "docs"
Requires-Dist: pydata_sphinx_theme; extra == "docs"
Requires-Dist: sphinx-autoapi; extra == "docs"
Requires-Dist: sphinx-multiversion; extra == "docs"
Requires-Dist: sphinx_markdown_tables; extra == "docs"
Requires-Dist: sphinx_rtd_theme; extra == "docs"
Requires-Dist: sphinxcontrib-mermaid; extra == "docs"
Requires-Dist: sphinxcontrib-napoleon; extra == "docs"
Provides-Extra: dev
Requires-Dist: black; extra == "dev"
Requires-Dist: ipython; extra == "dev"
Requires-Dist: pre-commit; extra == "dev"
Requires-Dist: pylint; extra == "dev"
Requires-Dist: pyupgrade; extra == "dev"
Requires-Dist: pytest-durations; extra == "dev"
Requires-Dist: pytest-icdiff; extra == "dev"
Requires-Dist: pytest-testmon; extra == "dev"
Provides-Extra: pypi
Requires-Dist: build; extra == "pypi"
Requires-Dist: setuptools_scm[toml]; extra == "pypi"
Requires-Dist: wheel; extra == "pypi"
Provides-Extra: notebooks
Requires-Dist: ipython; extra == "notebooks"
Requires-Dist: ipywidgets; extra == "notebooks"
Requires-Dist: jupyter_contrib_nbextensions; extra == "notebooks"
Requires-Dist: jupyterthemes; extra == "notebooks"
Dynamic: license-file
